<?xml version="1.0" encoding="UTF-8" ?>
<!DOCTYPE mapper PUBLIC "-//mybatis.org//DTD Mapper 3.0//EN" "http://mybatis.org/dtd/mybatis-3-mapper.dtd">

<mapper namespace="board">
	<insert id="insert" parameterType="boardvo">
		<![CDATA[
			insert
		      into board
			values (null, ?, ?, 0, now(), (select ifnull(max(g_no), 0) + 1 from board a), 1, 0, ?)
		]]>
		<selectKey keyProperty="id" resultType="long" order="AFTER">
			<![CDATA[
				select last_insert_id();
			]]>
		</selectKey>
	</insert>

	<insert id="insert" parameterType="guestbookvo">
		<![CDATA[

		]]>

	</insert>

	<delete id="deleteByIdAndPassword" parameterType="map">
		<![CDATA[

		]]>
	</delete>
</mapper>
